django_fragments/__init__.py
django_fragments/apps.py
django_fragments/forms.py
django_fragments/static/doDropCommon.js
django_fragments/static/doDropMenu.js
django_fragments/static/doDropSelect.js
django_fragments/static/doTheme.js
django_fragments/templates/_nav.html
django_fragments/templates/about.html
django_fragments/templates/base_template.html
django_fragments/templates/contact.html
django_fragments/templates/down-list.html
django_fragments/templates/home.html
django_fragments/templates/msg.html
django_fragments/templates/msg_form.html
django_fragments/templates/svg/heroicons_moon.html
django_fragments/templates/svg/heroicons_sun.html
django_fragments/templates/svg/heroicons_x_mark_mini.html
django_fragments/templates/test_snippet.html
django_fragments/templatetags/__init__.py
django_fragments/templatetags/fragments.py
django_fragments/templatetags/helpers.py
django_fragments/templatetags/og.py
django_fragments/templatetags/utils/__init__.py
django_fragments/templatetags/utils/filter_attrs.py
django_fragments/templatetags/utils/wrap_svg.py
django_fragments/tests.py
django_fragments/urls.py
django_fragments/utils.py
django_fragments/views.py
django_fragments-0.1.9.dist-info/LICENSE
django_fragments-0.1.9.dist-info/METADATA
django_fragments-0.1.9.dist-info/WHEEL
django_fragments-0.1.9.dist-info/RECORD
