Metadata-Version: 2.1
Name: django-fragments
Version: 0.1.9
Summary: Custom template tags for common html idioms in Django.
Home-page: https://mv3.dev
Author: Marcelino G. Veloso III
Author-email: mars@veloso.one
Requires-Python: >=3.11,<4.0
Classifier: Development Status :: 4 - Beta
Classifier: Framework :: Pytest
Classifier: Programming Language :: Python :: 3
Classifier: Programming Language :: Python :: 3.11
Classifier: Typing :: Typed
Requires-Dist: beautifulsoup4 (>=4.12.2,<5.0.0)
Requires-Dist: django (>=4.2,<5.0)
Requires-Dist: markdown (>=3.3.7,<4.0.0)
Project-URL: Documentation, https://justmars.github.io/django-fragments
Project-URL: Repository, https://github.com/justmars/django-fragments
